blurhash_python-1.2.2.dist-info/top_level.txt
blurhash_python-1.2.2.dist-info/METADATA
blurhash_python-1.2.2.dist-info/RECORD
blurhash_python-1.2.2.dist-info/LICENSE
blurhash_python-1.2.2.dist-info/WHEEL
blurhash/_version.py
blurhash/__init__.py
blurhash/_functions.abi3.so
