Metadata-Version: 2.1
Name: blurhash-python
Version: 1.2.2
Summary: BlurHash encoder implementation for Python
Home-page: https://blurha.sh
Author: Atte Lautanala
Author-email: atte.lautanala@wolt.com
Classifier: Development Status :: 5 - Production/Stable
Classifier: License :: OSI Approved :: MIT License
Classifier: Operating System :: OS Independent
Classifier: Programming Language :: Python :: 3
Classifier: Programming Language :: Python :: 3.8
Classifier: Programming Language :: Python :: 3.9
Classifier: Programming Language :: Python :: 3.10
Classifier: Programming Language :: Python :: 3.11
Classifier: Programming Language :: Python :: 3.12
License-File: LICENSE
Requires-Dist: cffi
Requires-Dist: Pillow
Requires-Dist: six
Provides-Extra: testing
Requires-Dist: pytest ; extra == 'testing'
